botparse.py
setup.py
BotParse.egg-info/PKG-INFO
BotParse.egg-info/SOURCES.txt
BotParse.egg-info/dependency_links.txt
BotParse.egg-info/top_level.txt