Metadata-Version: 1.1
Name: BotParse
Version: 0.1.0
Summary: A modified version of argparse to make bot making easer
Home-page: https://github.com/cameronbwhite/BotParse
Author: Cameron Brandon White
Author-email: cameronbwhite90@gmail.com
License: BSD
Download-URL: https://github.com/cameronbwhite/BotParse/downloads
Platform: UNKNOWN
Classifier: Development Status :: 4 - Beta
Classifier: License :: OSI Approved :: BSD License
Classifier: Intended Audience :: Developers
Classifier: Operating System :: OS Independent
Classifier: Programming Language :: Python :: 2.7
Classifier: Topic :: Software Development :: Libraries :: Python Modules
Provides: BotParse
